{
    "result": {
        "list" : [
            {
                "no" : 10,
                "title" : "public/assets/data/notice.json - 10",
                "link" : "/notice",
                "file" : "/notice",
                "date" : "1983-07-11"
            },
            {
                "no" : 9,
                "title" : "public/assets/data/notice.json - 9",
                "link" : "/notice",
                "file" : "/notice",
                "date" : "1983-07-11"
            },
            {
                "no" : 8,
                "title" : "public/assets/data/notice.json - 8",
                "link" : "/notice",
                "file" : "/notice",
                "date" : "1983-07-11"
            },
            {
                "no" : 7,
                "title" : "public/assets/data/notice.json - 7",
                "link" : "/notice",
                "file" : "/notice",
                "date" : "1983-07-11"
            },
            {
                "no" : 6,
                "title" : "public/assets/data/notice.json - 6",
                "link" : "/notice",
                "file" : "/notice",
                "date" : "1983-07-11"
            },
            {
                "no" : 5,
                "title" : "public/assets/data/notice.json - 5",
                "link" : "/notice",
                "file" : "/notice",
                "date" : "1983-07-11"
            },
            {
                "no" : 4,
                "title" : "public/assets/data/notice.json - 4",
                "link" : "/notice",
                "file" : "/notice",
                "date" : "1983-07-11"
            },
            {
                "no" : 3,
                "title" : "public/assets/data/notice.json - 3",
                "link" : "/notice",
                "file" : "/notice",
                "date" : "1983-07-11"
            },
            {
                "no" : 2,
                "title" : "public/assets/data/notice.json - 2",
                "link" : "/notice",
                "file" : "/notice",
                "date" : "1983-07-11"
            },
            {
                "no" : 1,
                "title" : "public/assets/data/notice.json - 1",
                "link" : "/notice",
                "file" : "/notice",
                "date" : "1983-07-11"
            }
        ]
    }
}